elevate3d/__init__.py
elevate3d/app.py
elevate3d/config.py
elevate3d/run_pipeline.py
elevate3d/core/__init__.py
elevate3d/core/models.py
elevate3d/core/deepforest/__init__.py
elevate3d/core/deepforest/deepforest.py
elevate3d/core/dsm/__init__.py
elevate3d/core/dsm/dsm2dtm.py
elevate3d/core/dsm/predict_dsm.py
elevate3d/core/mask/__init__.py
elevate3d/core/mask/predict_mask.py
elevate3d/core/mesh/__init__.py
elevate3d/core/mesh/building.py
elevate3d/core/mesh/generate_building_mesh.py
elevate3d/core/mesh/generate_mesh.py
elevate3d/core/mesh/generate_terrain_mesh.py
elevate3d/core/mesh/generate_tree_mesh.py
elevate3d/core/mesh/texture_manager.py
elevate3d/core/roof/__init__.py
elevate3d/core/roof/predict_roof.py
elevate3d/templates/index.html
elevate3d/utils/__init__.py
elevate3d/utils/download_manager.py
elevate3d-0.5.1.dist-info/licenses/LICENSE
elevate3d-0.5.1.dist-info/METADATA
elevate3d-0.5.1.dist-info/WHEEL
elevate3d-0.5.1.dist-info/entry_points.txt
elevate3d-0.5.1.dist-info/top_level.txt
elevate3d-0.5.1.dist-info/RECORD
