Metadata-Version: 2.4
Name: elevate3d
Version: 0.5.1
Summary: 3D terrain and structure reconstruction from single RGB images
Home-page: https://github.com/krdgomer/elevate3d
Author: Ömer Can Karadağ
Author-email: krdg.omercan@hotmail.com
Classifier: Programming Language :: Python :: 3
Classifier: License :: OSI Approved :: MIT License
Classifier: Operating System :: OS Independent
Requires-Python: >=3.8
License-File: LICENSE
Requires-Dist: open3d
Requires-Dist: numpy
Requires-Dist: pillow
Requires-Dist: opencv-python
Requires-Dist: torch
Requires-Dist: albumentations
Requires-Dist: deepforest
Requires-Dist: scikit-image
Requires-Dist: huggingface_hub
Requires-Dist: flask
Requires-Dist: trimesh
Requires-Dist: matplotlib
Requires-Dist: scipy
Dynamic: author
Dynamic: author-email
Dynamic: classifier
Dynamic: description
Dynamic: description-content-type
Dynamic: home-page
Dynamic: license-file
Dynamic: requires-dist
Dynamic: requires-python
Dynamic: summary
